pypkgs_dj/__init__.py
pypkgs_dj/pypkgs_dj.py
pypkgs_dj-0.1.0.dist-info/LICENSE
pypkgs_dj-0.1.0.dist-info/WHEEL
pypkgs_dj-0.1.0.dist-info/METADATA
pypkgs_dj-0.1.0.dist-info/RECORD
