Metadata-Version: 2.1
Name: pypkgs-dj
Version: 0.1.0
Summary: This is the initial step of creating a toy Python package.
License: MIT
Author: Jianru D
Author-email: dengjr1509@gmail.com
Requires-Python: >=3.8,<4.0
Classifier: License :: OSI Approved :: MIT License
Classifier: Programming Language :: Python :: 3
Classifier: Programming Language :: Python :: 3.8
Classifier: Programming Language :: Python :: 3.9
Requires-Dist: pandas (>=1.2.2,<2.0.0)
